{
  "logoType": "lucideIcon",
  "logo": {
    "lucideIcon": "pencil",
    "imagePath": "",
    "imageLink": ""
  },
  "logoScale": 1.2,
  "iconColorType": "default",
  "wordmark": "0x4248 Notebook",
  "customFont": "interfaceFont",
  "fontSize": "4em",
  "fontColorType": "default",
  "fontWeight": 600,
  "maxResults": 5,
  "showbookmarkedFiles": true,
  "showRecentFiles": false,
  "maxRecentFiles": 5,
  "storeRecentFile": true,
  "showPath": true,
  "selectionHighlight": "default",
  "showShortcuts": true,
  "markdownOnly": false,
  "unresolvedLinks": false,
  "recentFilesStore": [
    {
      "filepath": "README.md",
      "timestamp": 1731624183906
    },
    {
      "filepath": "99 Private/as-and-a-level-ocr-computer-science.pdf",
      "timestamp": 1731624182812
    },
    {
      "filepath": "01 Areas/Computer Science/4 Exchanging data/15 Compression, Encryption and Hashing/Drawings/Caesar cipher drawing.md",
      "timestamp": 1731624158161
    },
    {
      "filepath": "01 Areas/Computer Science/4 Exchanging data/15 Compression, Encryption and Hashing/Caesar Cipher.md",
      "timestamp": 1731624154289
    },
    {
      "filepath": "01 Areas/Computer Science/4 Exchanging data/15 Compression, Encryption and Hashing/Asymetric Encryption.md",
      "timestamp": 1731624141354
    }
  ],
  "bookmarkedFileStore": [],
  "searchDelay": 0,
  "replaceNewTabs": true,
  "newTabOnStart": false,
  "closePreviousSessionTabs": false,
  "omnisearch": false,
  "showOmnisearchExcerpt": true,
  "font": "\"Bai \""
}