{
  "cascadeColors": true,
  "colorBackground": false,
  "palette": [
    {
      "id": "ZM4_HOZZMs3HRQ6CF9AqM",
      "name": "Green Cyan",
      "value": "#42ffe9"
    },
    {
      "id": "G2nRaHNAs6UoZLQSqCzKv",
      "name": "Light blue",
      "value": "#42e0ff"
    },
    {
      "id": "9IW26_42YlHLegoipPbfv",
      "name": "Pale Blue",
      "value": "#3dbeff"
    },
    {
      "id": "vZV9Ij7lzIyaE4EpF82eM",
      "name": "Blue",
      "value": "#3da1ff"
    },
    {
      "id": "q9FhUoJFFDzlyDtyr3PyB",
      "name": "Deep Blue",
      "value": "#3e63f4"
    },
    {
      "id": "5TEp2YXVMecjIoJDqI3cq",
      "name": "Gray",
      "value": "#616161"
    }
  ],
  "fileColors": [
    {
      "path": "00 Maps",
      "color": "ZM4_HOZZMs3HRQ6CF9AqM"
    },
    {
      "path": "01 Areas",
      "color": "G2nRaHNAs6UoZLQSqCzKv"
    },
    {
      "path": "02 Fleeting",
      "color": "9IW26_42YlHLegoipPbfv"
    },
    {
      "path": "03 Archive",
      "color": "vZV9Ij7lzIyaE4EpF82eM"
    },
    {
      "path": "04 Meta",
      "color": "5TEp2YXVMecjIoJDqI3cq"
    },
    {
      "path": "README.md",
      "color": "5TEp2YXVMecjIoJDqI3cq"
    },
    {
      "path": "99 Private",
      "color": "5TEp2YXVMecjIoJDqI3cq"
    }
  ]
}